{
  "schemaVersion": 1,
  "generatedAt": "2026-05-30T15:27:56+00:00",
  "source": "Temp/web_ref.html",
  "character": {
    "slug": "zhoufei",
    "command": "zhoufei",
    "name": "周妃",
    "displayName": {
      "zhHans": "周妃",
      "zhHant": "周妃"
    },
    "names": [
      "周妃"
    ],
    "displayNames": [
      {
        "zhHans": "周妃",
        "zhHant": "周妃"
      }
    ],
    "ids": [
      "411"
    ],
    "sourceNames": [
      "周妃"
    ],
    "displaySourceNames": [
      {
        "zhHans": "周妃",
        "zhHant": "周妃"
      }
    ],
    "sourceIds": [
      "411"
    ],
    "searchNames": [
      "zhoufei",
      "周妃"
    ],
    "lineCount": 35,
    "groups": [
      {
        "slug": "dead",
        "name": "阵亡",
        "displayName": {
          "zhHans": "阵亡",
          "zhHant": "陣亡"
        },
        "ids": [
          "1"
        ],
        "lineCount": 7
      },
      {
        "slug": "spell-820",
        "name": "良姻",
        "displayName": {
          "zhHans": "良姻",
          "zhHant": "良姻"
        },
        "ids": [
          "820"
        ],
        "lineCount": 14
      },
      {
        "slug": "spell-821",
        "name": "箜声",
        "displayName": {
          "zhHans": "箜声",
          "zhHant": "箜聲"
        },
        "ids": [
          "821"
        ],
        "lineCount": 14
      }
    ],
    "skins": [
      {
        "slug": "41107",
        "ids": [
          "41107"
        ],
        "name": "41107",
        "displayName": {
          "zhHans": "41107",
          "zhHant": "41107"
        },
        "lineCount": 5
      },
      {
        "slug": "skin-1",
        "ids": [
          "-1"
        ],
        "name": "原画",
        "displayName": {
          "zhHans": "原画",
          "zhHant": "原畫"
        },
        "lineCount": 5
      },
      {
        "slug": "skin-41106",
        "ids": [
          "41106"
        ],
        "name": "清风轻拂",
        "displayName": {
          "zhHans": "清风轻拂",
          "zhHant": "清風輕拂"
        },
        "lineCount": 5
      },
      {
        "slug": "skin-41101",
        "ids": [
          "41101"
        ],
        "name": "箜灵寻音",
        "displayName": {
          "zhHans": "箜灵寻音",
          "zhHant": "箜靈尋音"
        },
        "lineCount": 5
      },
      {
        "slug": "skin-41102",
        "ids": [
          "41102"
        ],
        "name": "箜篌箜声",
        "displayName": {
          "zhHans": "箜篌箜声",
          "zhHant": "箜篌箜聲"
        },
        "lineCount": 5
      },
      {
        "slug": "skin-41104",
        "ids": [
          "41104"
        ],
        "name": "金枝玉叶",
        "displayName": {
          "zhHans": "金枝玉叶",
          "zhHant": "金枝玉葉"
        },
        "lineCount": 5
      },
      {
        "slug": "skin-41105",
        "ids": [
          "41105"
        ],
        "name": "金秋霁月",
        "displayName": {
          "zhHans": "金秋霁月",
          "zhHant": "金秋霽月"
        },
        "lineCount": 5
      },
      {
        "slug": "skin-41103",
        "ids": [
          "41103"
        ],
        "name": "鹊星夕情",
        "displayName": {
          "zhHans": "鹊星夕情",
          "zhHant": "鵲星夕情"
        },
        "lineCount": 5
      }
    ],
    "endpoints": {
      "detail": "api/v1/characters/zhoufei.json",
      "lines": "api/v1/characters/zhoufei/lines.json"
    }
  }
}
