{
  "schemaVersion": 1,
  "generatedAt": "2026-05-30T15:27:56+00:00",
  "character": {
    "slug": "jiedaqiao",
    "command": "jiedaqiao",
    "name": "界大乔",
    "displayName": {
      "zhHans": "界大乔",
      "zhHant": "界大喬"
    },
    "names": [
      "界大乔",
      "大乔"
    ],
    "displayNames": [
      {
        "zhHans": "界大乔",
        "zhHant": "界大喬"
      },
      {
        "zhHans": "大乔",
        "zhHant": "大喬"
      }
    ],
    "ids": [
      "309",
      "13"
    ],
    "sourceNames": [
      "界大乔",
      "大乔"
    ],
    "displaySourceNames": [
      {
        "zhHans": "界大乔",
        "zhHant": "界大喬"
      },
      {
        "zhHans": "大乔",
        "zhHant": "大喬"
      }
    ],
    "sourceIds": [
      "309",
      "13"
    ],
    "searchNames": [
      "jiedaqiao",
      "界大乔",
      "界大喬",
      "大乔",
      "大喬"
    ],
    "lineCount": 40,
    "groups": [
      {
        "slug": "dead",
        "name": "阵亡",
        "displayName": {
          "zhHans": "阵亡",
          "zhHant": "陣亡"
        },
        "lineCount": 8,
        "endpoint": "api/v1/tts/characters/jiedaqiao/groups/dead.json"
      },
      {
        "slug": "spell-60-714",
        "name": "国色",
        "displayName": {
          "zhHans": "国色",
          "zhHant": "國色"
        },
        "lineCount": 14,
        "endpoint": "api/v1/tts/characters/jiedaqiao/groups/spell-60-714.json"
      },
      {
        "slug": "spell-61",
        "name": "流离",
        "displayName": {
          "zhHans": "流离",
          "zhHant": "流離"
        },
        "lineCount": 16,
        "endpoint": "api/v1/tts/characters/jiedaqiao/groups/spell-61.json"
      },
      {
        "slug": "spell-714",
        "name": "国色",
        "displayName": {
          "zhHans": "国色",
          "zhHant": "國色"
        },
        "lineCount": 2,
        "endpoint": "api/v1/tts/characters/jiedaqiao/groups/spell-714.json"
      }
    ],
    "skins": [
      {
        "slug": "skin-1",
        "name": "原画",
        "displayName": {
          "zhHans": "原画",
          "zhHant": "原畫"
        },
        "lineCount": 5,
        "endpoint": "api/v1/tts/characters/jiedaqiao/skins/skin-1.json"
      },
      {
        "slug": "skin-30908",
        "name": "国色留符",
        "displayName": {
          "zhHans": "国色留符",
          "zhHant": "國色留符"
        },
        "lineCount": 5,
        "endpoint": "api/v1/tts/characters/jiedaqiao/skins/skin-30908.json"
      },
      {
        "slug": "skin-30906",
        "name": "思君情长",
        "displayName": {
          "zhHans": "思君情长",
          "zhHant": "思君情長"
        },
        "lineCount": 5,
        "endpoint": "api/v1/tts/characters/jiedaqiao/skins/skin-30906.json"
      },
      {
        "slug": "skin-30912",
        "name": "清萧清丽",
        "displayName": {
          "zhHans": "清萧清丽",
          "zhHant": "清蕭清麗"
        },
        "lineCount": 5,
        "endpoint": "api/v1/tts/characters/jiedaqiao/skins/skin-30912.json"
      },
      {
        "slug": "skin-30909",
        "name": "绮裙轻袖",
        "displayName": {
          "zhHans": "绮裙轻袖",
          "zhHant": "綺裙輕袖"
        },
        "lineCount": 5,
        "endpoint": "api/v1/tts/characters/jiedaqiao/skins/skin-30909.json"
      },
      {
        "slug": "skin-30901",
        "name": "舞动生花",
        "displayName": {
          "zhHans": "舞动生花",
          "zhHant": "舞動生花"
        },
        "lineCount": 5,
        "endpoint": "api/v1/tts/characters/jiedaqiao/skins/skin-30901.json"
      },
      {
        "slug": "skin-30901-30909",
        "name": "舞动生花,绮裙轻袖",
        "displayName": {
          "zhHans": "舞动生花,绮裙轻袖",
          "zhHant": "舞動生花,綺裙輕袖"
        },
        "lineCount": 5,
        "endpoint": "api/v1/tts/characters/jiedaqiao/skins/skin-30901-30909.json"
      },
      {
        "slug": "skin-30911",
        "name": "良辰佳夕",
        "displayName": {
          "zhHans": "良辰佳夕",
          "zhHant": "良辰佳夕"
        },
        "lineCount": 5,
        "endpoint": "api/v1/tts/characters/jiedaqiao/skins/skin-30911.json"
      },
      {
        "slug": "skin-30903",
        "name": "花好月圆",
        "displayName": {
          "zhHans": "花好月圆",
          "zhHant": "花好月圓"
        },
        "lineCount": 5,
        "endpoint": "api/v1/tts/characters/jiedaqiao/skins/skin-30903.json"
      },
      {
        "slug": "skin-30904",
        "name": "薄媚摘偏",
        "displayName": {
          "zhHans": "薄媚摘偏",
          "zhHant": "薄媚摘偏"
        },
        "lineCount": 5,
        "endpoint": "api/v1/tts/characters/jiedaqiao/skins/skin-30904.json"
      },
      {
        "slug": "skin-30904-30908-30910",
        "name": "薄媚摘偏,国色留符,赏蝶思情",
        "displayName": {
          "zhHans": "薄媚摘偏,国色留符,赏蝶思情",
          "zhHant": "薄媚摘偏,國色留符,賞蝶思情"
        },
        "lineCount": 5,
        "endpoint": "api/v1/tts/characters/jiedaqiao/skins/skin-30904-30908-30910.json"
      },
      {
        "slug": "skin-30910",
        "name": "赏蝶思情",
        "displayName": {
          "zhHans": "赏蝶思情",
          "zhHant": "賞蝶思情"
        },
        "lineCount": 5,
        "endpoint": "api/v1/tts/characters/jiedaqiao/skins/skin-30910.json"
      },
      {
        "slug": "skin-30907",
        "name": "软语花香",
        "displayName": {
          "zhHans": "软语花香",
          "zhHant": "軟語花香"
        },
        "lineCount": 5,
        "endpoint": "api/v1/tts/characters/jiedaqiao/skins/skin-30907.json"
      }
    ],
    "endpoints": {
      "detail": "api/v1/tts/characters/jiedaqiao.json",
      "groups": "api/v1/tts/characters/jiedaqiao/groups/{groupSlug}.json",
      "skins": "api/v1/tts/characters/jiedaqiao/skins/{skinSlug}.json"
    }
  },
  "skin": {
    "slug": "skin-30901-30909",
    "name": "舞动生花,绮裙轻袖",
    "displayName": {
      "zhHans": "舞动生花,绮裙轻袖",
      "zhHant": "舞動生花,綺裙輕袖"
    },
    "lineCount": 5,
    "endpoint": "api/v1/tts/characters/jiedaqiao/skins/skin-30901-30909.json"
  },
  "lineCount": 5,
  "lines": [
    {
      "id": "jiedaqiao--309jiedaqiao--3dead01",
      "resourceId": "309jiedaqiao/3dead01",
      "text": "哼唔~哼唔~",
      "textLocalized": {
        "zhHans": "哼唔~哼唔~",
        "zhHant": "哼唔~哼唔~"
      },
      "group": {
        "slug": "dead",
        "name": "阵亡",
        "displayName": {
          "zhHans": "阵亡",
          "zhHant": "陣亡"
        }
      },
      "skins": [
        {
          "slug": "skin-30909",
          "name": "绮裙轻袖",
          "displayName": {
            "zhHans": "绮裙轻袖",
            "zhHant": "綺裙輕袖"
          }
        },
        {
          "slug": "skin-30901",
          "name": "舞动生花",
          "displayName": {
            "zhHans": "舞动生花",
            "zhHant": "舞動生花"
          }
        },
        {
          "slug": "skin-30901-30909",
          "name": "舞动生花,绮裙轻袖",
          "displayName": {
            "zhHans": "舞动生花,绮裙轻袖",
            "zhHant": "舞動生花,綺裙輕袖"
          }
        }
      ],
      "audio": {
        "cached": "audio-cache/voice/spell/309jiedaqiao-3dbde84e/3dead01-f6a89a91.mp3",
        "remote": "https://web.sanguosha.com/220/h5_2/res/runtime/pc/voice/spell/309jiedaqiao/3dead01.mp3",
        "available": {
          "cached": true,
          "remote": true
        }
      }
    },
    {
      "id": "jiedaqiao--309jiedaqiao--3skill1_1",
      "resourceId": "309jiedaqiao/3skill1_1",
      "text": "征战辛苦，请休息吧~",
      "textLocalized": {
        "zhHans": "征战辛苦，请休息吧~",
        "zhHant": "征戰辛苦，請休息吧~"
      },
      "group": {
        "slug": "spell-60-714",
        "name": "国色",
        "displayName": {
          "zhHans": "国色",
          "zhHant": "國色"
        }
      },
      "skins": [
        {
          "slug": "skin-30909",
          "name": "绮裙轻袖",
          "displayName": {
            "zhHans": "绮裙轻袖",
            "zhHant": "綺裙輕袖"
          }
        },
        {
          "slug": "skin-30901",
          "name": "舞动生花",
          "displayName": {
            "zhHans": "舞动生花",
            "zhHant": "舞動生花"
          }
        },
        {
          "slug": "skin-30901-30909",
          "name": "舞动生花,绮裙轻袖",
          "displayName": {
            "zhHans": "舞动生花,绮裙轻袖",
            "zhHant": "舞動生花,綺裙輕袖"
          }
        }
      ],
      "audio": {
        "cached": "audio-cache/voice/spell/309jiedaqiao-3dbde84e/3skill1-1-b9fc751f.mp3",
        "remote": "https://web.sanguosha.com/220/h5_2/res/runtime/pc/voice/spell/309jiedaqiao/3skill1_1.mp3",
        "available": {
          "cached": true,
          "remote": true
        }
      }
    },
    {
      "id": "jiedaqiao--309jiedaqiao--3skill1_2",
      "resourceId": "309jiedaqiao/3skill1_2",
      "text": "再坚持一下~",
      "textLocalized": {
        "zhHans": "再坚持一下~",
        "zhHant": "再堅持一下~"
      },
      "group": {
        "slug": "spell-60-714",
        "name": "国色",
        "displayName": {
          "zhHans": "国色",
          "zhHant": "國色"
        }
      },
      "skins": [
        {
          "slug": "skin-30909",
          "name": "绮裙轻袖",
          "displayName": {
            "zhHans": "绮裙轻袖",
            "zhHant": "綺裙輕袖"
          }
        },
        {
          "slug": "skin-30901",
          "name": "舞动生花",
          "displayName": {
            "zhHans": "舞动生花",
            "zhHant": "舞動生花"
          }
        },
        {
          "slug": "skin-30901-30909",
          "name": "舞动生花,绮裙轻袖",
          "displayName": {
            "zhHans": "舞动生花,绮裙轻袖",
            "zhHant": "舞動生花,綺裙輕袖"
          }
        }
      ],
      "audio": {
        "cached": "audio-cache/voice/spell/309jiedaqiao-3dbde84e/3skill1-2-b8925c7a.mp3",
        "remote": "https://web.sanguosha.com/220/h5_2/res/runtime/pc/voice/spell/309jiedaqiao/3skill1_2.mp3",
        "available": {
          "cached": true,
          "remote": true
        }
      }
    },
    {
      "id": "jiedaqiao--309jiedaqiao--3skill2_1",
      "resourceId": "309jiedaqiao/3skill2_1",
      "text": "哼！欺我江东无人吗？",
      "textLocalized": {
        "zhHans": "哼！欺我江东无人吗？",
        "zhHant": "哼！欺我江東無人嗎？"
      },
      "group": {
        "slug": "spell-61",
        "name": "流离",
        "displayName": {
          "zhHans": "流离",
          "zhHant": "流離"
        }
      },
      "skins": [
        {
          "slug": "skin-30909",
          "name": "绮裙轻袖",
          "displayName": {
            "zhHans": "绮裙轻袖",
            "zhHant": "綺裙輕袖"
          }
        },
        {
          "slug": "skin-30901",
          "name": "舞动生花",
          "displayName": {
            "zhHans": "舞动生花",
            "zhHant": "舞動生花"
          }
        },
        {
          "slug": "skin-30901-30909",
          "name": "舞动生花,绮裙轻袖",
          "displayName": {
            "zhHans": "舞动生花,绮裙轻袖",
            "zhHant": "舞動生花,綺裙輕袖"
          }
        }
      ],
      "audio": {
        "cached": "audio-cache/voice/spell/309jiedaqiao-3dbde84e/3skill2-1-75933275.mp3",
        "remote": "https://web.sanguosha.com/220/h5_2/res/runtime/pc/voice/spell/309jiedaqiao/3skill2_1.mp3",
        "available": {
          "cached": true,
          "remote": true
        }
      }
    },
    {
      "id": "jiedaqiao--309jiedaqiao--3skill2_2",
      "resourceId": "309jiedaqiao/3skill2_2",
      "text": "女孩子不是怎么好欺负的~",
      "textLocalized": {
        "zhHans": "女孩子不是怎么好欺负的~",
        "zhHant": "女孩子不是怎麼好欺負的~"
      },
      "group": {
        "slug": "spell-61",
        "name": "流离",
        "displayName": {
          "zhHans": "流离",
          "zhHant": "流離"
        }
      },
      "skins": [
        {
          "slug": "skin-30909",
          "name": "绮裙轻袖",
          "displayName": {
            "zhHans": "绮裙轻袖",
            "zhHant": "綺裙輕袖"
          }
        },
        {
          "slug": "skin-30901",
          "name": "舞动生花",
          "displayName": {
            "zhHans": "舞动生花",
            "zhHant": "舞動生花"
          }
        },
        {
          "slug": "skin-30901-30909",
          "name": "舞动生花,绮裙轻袖",
          "displayName": {
            "zhHans": "舞动生花,绮裙轻袖",
            "zhHant": "舞動生花,綺裙輕袖"
          }
        }
      ],
      "audio": {
        "cached": "audio-cache/voice/spell/309jiedaqiao-3dbde84e/3skill2-2-f96d06aa.mp3",
        "remote": "https://web.sanguosha.com/220/h5_2/res/runtime/pc/voice/spell/309jiedaqiao/3skill2_2.mp3",
        "available": {
          "cached": true,
          "remote": true
        }
      }
    }
  ]
}
