{
  "schemaVersion": 1,
  "generatedAt": "2026-05-30T15:27:56+00:00",
  "character": {
    "slug": "caochun",
    "command": "caochun",
    "name": "曹纯",
    "displayName": {
      "zhHans": "曹纯",
      "zhHant": "曹純"
    },
    "names": [
      "曹纯"
    ],
    "displayNames": [
      {
        "zhHans": "曹纯",
        "zhHant": "曹純"
      }
    ],
    "ids": [
      "426"
    ],
    "sourceNames": [
      "曹纯"
    ],
    "displaySourceNames": [
      {
        "zhHans": "曹纯",
        "zhHant": "曹純"
      }
    ],
    "sourceIds": [
      "426"
    ],
    "searchNames": [
      "caochun",
      "曹纯",
      "曹純"
    ],
    "lineCount": 9,
    "groups": [
      {
        "slug": "dead",
        "name": "阵亡",
        "displayName": {
          "zhHans": "阵亡",
          "zhHant": "陣亡"
        },
        "ids": [
          "1"
        ],
        "lineCount": 3
      },
      {
        "slug": "spell-868",
        "name": "缮甲",
        "displayName": {
          "zhHans": "缮甲",
          "zhHant": "繕甲"
        },
        "ids": [
          "868"
        ],
        "lineCount": 6
      }
    ],
    "skins": [
      {
        "slug": "skin-42602",
        "ids": [
          "42602"
        ],
        "name": "亲率征兵",
        "displayName": {
          "zhHans": "亲率征兵",
          "zhHant": "親率徵兵"
        },
        "lineCount": 3
      },
      {
        "slug": "skin-1",
        "ids": [
          "-1"
        ],
        "name": "原画",
        "displayName": {
          "zhHans": "原画",
          "zhHant": "原畫"
        },
        "lineCount": 3
      },
      {
        "slug": "skin-42601",
        "ids": [
          "42601"
        ],
        "name": "虎豹英骑",
        "displayName": {
          "zhHans": "虎豹英骑",
          "zhHant": "虎豹英騎"
        },
        "lineCount": 3
      }
    ],
    "endpoints": {
      "detail": "api/v1/characters/caochun.json",
      "lines": "api/v1/characters/caochun/lines.json"
    }
  },
  "group": {
    "slug": "dead",
    "ids": [
      "1"
    ],
    "name": "阵亡",
    "displayName": {
      "zhHans": "阵亡",
      "zhHant": "陣亡"
    },
    "names": [
      "阵亡"
    ],
    "displayNames": [
      {
        "zhHans": "阵亡",
        "zhHant": "陣亡"
      }
    ]
  },
  "lineCount": 3,
  "lines": [
    {
      "id": "caochun--426caochun--4dead01",
      "resourceId": "426caochun/4dead01",
      "text": "三属之下，竟也护不住我性命。",
      "textLocalized": {
        "zhHans": "三属之下，竟也护不住我性命。",
        "zhHant": "三屬之下，竟也護不住我性命。"
      },
      "character": {
        "slug": "caochun",
        "command": "caochun",
        "id": "426",
        "ids": [
          "426"
        ],
        "name": "曹纯",
        "displayName": {
          "zhHans": "曹纯",
          "zhHant": "曹純"
        },
        "names": [
          "曹纯"
        ],
        "displayNames": [
          {
            "zhHans": "曹纯",
            "zhHant": "曹純"
          }
        ],
        "sourceIds": [
          "426"
        ],
        "sourceNames": [
          "曹纯"
        ],
        "displaySourceNames": [
          {
            "zhHans": "曹纯",
            "zhHant": "曹純"
          }
        ],
        "searchNames": [
          "曹纯",
          "曹純",
          "caochun"
        ]
      },
      "group": {
        "slug": "dead",
        "ids": [
          "1"
        ],
        "name": "阵亡",
        "displayName": {
          "zhHans": "阵亡",
          "zhHant": "陣亡"
        },
        "names": [
          "阵亡"
        ],
        "displayNames": [
          {
            "zhHans": "阵亡",
            "zhHant": "陣亡"
          }
        ]
      },
      "skin": {
        "slug": "skin-42602",
        "ids": [
          "42602"
        ],
        "name": "亲率征兵",
        "displayName": {
          "zhHans": "亲率征兵",
          "zhHant": "親率徵兵"
        },
        "names": [
          "亲率征兵"
        ],
        "displayNames": [
          {
            "zhHans": "亲率征兵",
            "zhHant": "親率徵兵"
          }
        ]
      },
      "skins": [
        {
          "slug": "skin-42602",
          "id": "42602",
          "ids": [
            "42602"
          ],
          "name": "亲率征兵",
          "displayName": {
            "zhHans": "亲率征兵",
            "zhHant": "親率徵兵"
          },
          "names": [
            "亲率征兵"
          ],
          "displayNames": [
            {
              "zhHans": "亲率征兵",
              "zhHant": "親率徵兵"
            }
          ]
        }
      ],
      "source": {
        "characterKey": "426",
        "skinKey": "42602",
        "spellKey": "1",
        "rowIndex": 1,
        "characterNames": [
          "曹纯"
        ],
        "skinNames": [
          "亲率征兵"
        ]
      },
      "audio": {
        "cached": "audio-cache/voice/spell/426caochun-c825aeb5/4dead01-d94a0b4a.mp3",
        "remote": "https://web.sanguosha.com/220/h5_2/res/runtime/pc/voice/spell/426caochun/4dead01.mp3",
        "preferred": "cached",
        "available": {
          "cached": true,
          "remote": true
        }
      }
    },
    {
      "id": "caochun--426caochun--1dead01",
      "resourceId": "426caochun/1dead01",
      "text": "银甲在身，竟败于你手。",
      "textLocalized": {
        "zhHans": "银甲在身，竟败于你手。",
        "zhHant": "銀甲在身，竟敗於你手。"
      },
      "character": {
        "slug": "caochun",
        "command": "caochun",
        "id": "426",
        "ids": [
          "426"
        ],
        "name": "曹纯",
        "displayName": {
          "zhHans": "曹纯",
          "zhHant": "曹純"
        },
        "names": [
          "曹纯"
        ],
        "displayNames": [
          {
            "zhHans": "曹纯",
            "zhHant": "曹純"
          }
        ],
        "sourceIds": [
          "426"
        ],
        "sourceNames": [
          "曹纯"
        ],
        "displaySourceNames": [
          {
            "zhHans": "曹纯",
            "zhHant": "曹純"
          }
        ],
        "searchNames": [
          "曹纯",
          "曹純",
          "caochun"
        ]
      },
      "group": {
        "slug": "dead",
        "ids": [
          "1"
        ],
        "name": "阵亡",
        "displayName": {
          "zhHans": "阵亡",
          "zhHant": "陣亡"
        },
        "names": [
          "阵亡"
        ],
        "displayNames": [
          {
            "zhHans": "阵亡",
            "zhHant": "陣亡"
          }
        ]
      },
      "skin": {
        "slug": "skin-1",
        "ids": [
          "-1"
        ],
        "name": "原画",
        "displayName": {
          "zhHans": "原画",
          "zhHant": "原畫"
        },
        "names": [
          "原画"
        ],
        "displayNames": [
          {
            "zhHans": "原画",
            "zhHant": "原畫"
          }
        ]
      },
      "skins": [
        {
          "slug": "skin-1",
          "id": "-1",
          "ids": [
            "-1"
          ],
          "name": "原画",
          "displayName": {
            "zhHans": "原画",
            "zhHant": "原畫"
          },
          "names": [
            "原画"
          ],
          "displayNames": [
            {
              "zhHans": "原画",
              "zhHant": "原畫"
            }
          ]
        }
      ],
      "source": {
        "characterKey": "426",
        "skinKey": "-1",
        "spellKey": "1",
        "rowIndex": 1,
        "characterNames": [
          "曹纯"
        ],
        "skinNames": [
          "原画"
        ]
      },
      "audio": {
        "cached": "audio-cache/voice/spell/426caochun-c825aeb5/1dead01-71dcfcc3.mp3",
        "remote": "https://web.sanguosha.com/220/h5_2/res/runtime/pc/voice/spell/426caochun/1dead01.mp3",
        "preferred": "cached",
        "available": {
          "cached": true,
          "remote": true
        }
      }
    },
    {
      "id": "caochun--426caochun--3dead01",
      "resourceId": "426caochun/3dead01",
      "text": "宁可战死沙场，不可苟全安命。",
      "textLocalized": {
        "zhHans": "宁可战死沙场，不可苟全安命。",
        "zhHant": "寧可戰死沙場，不可苟全安命。"
      },
      "character": {
        "slug": "caochun",
        "command": "caochun",
        "id": "426",
        "ids": [
          "426"
        ],
        "name": "曹纯",
        "displayName": {
          "zhHans": "曹纯",
          "zhHant": "曹純"
        },
        "names": [
          "曹纯"
        ],
        "displayNames": [
          {
            "zhHans": "曹纯",
            "zhHant": "曹純"
          }
        ],
        "sourceIds": [
          "426"
        ],
        "sourceNames": [
          "曹纯"
        ],
        "displaySourceNames": [
          {
            "zhHans": "曹纯",
            "zhHant": "曹純"
          }
        ],
        "searchNames": [
          "曹纯",
          "曹純",
          "caochun"
        ]
      },
      "group": {
        "slug": "dead",
        "ids": [
          "1"
        ],
        "name": "阵亡",
        "displayName": {
          "zhHans": "阵亡",
          "zhHant": "陣亡"
        },
        "names": [
          "阵亡"
        ],
        "displayNames": [
          {
            "zhHans": "阵亡",
            "zhHant": "陣亡"
          }
        ]
      },
      "skin": {
        "slug": "skin-42601",
        "ids": [
          "42601"
        ],
        "name": "虎豹英骑",
        "displayName": {
          "zhHans": "虎豹英骑",
          "zhHant": "虎豹英騎"
        },
        "names": [
          "虎豹英骑"
        ],
        "displayNames": [
          {
            "zhHans": "虎豹英骑",
            "zhHant": "虎豹英騎"
          }
        ]
      },
      "skins": [
        {
          "slug": "skin-42601",
          "id": "42601",
          "ids": [
            "42601"
          ],
          "name": "虎豹英骑",
          "displayName": {
            "zhHans": "虎豹英骑",
            "zhHant": "虎豹英騎"
          },
          "names": [
            "虎豹英骑"
          ],
          "displayNames": [
            {
              "zhHans": "虎豹英骑",
              "zhHant": "虎豹英騎"
            }
          ]
        }
      ],
      "source": {
        "characterKey": "426",
        "skinKey": "42601",
        "spellKey": "1",
        "rowIndex": 1,
        "characterNames": [
          "曹纯"
        ],
        "skinNames": [
          "虎豹英骑"
        ]
      },
      "audio": {
        "cached": "audio-cache/voice/spell/426caochun-c825aeb5/3dead01-f6a89a91.mp3",
        "remote": "https://web.sanguosha.com/220/h5_2/res/runtime/pc/voice/spell/426caochun/3dead01.mp3",
        "preferred": "cached",
        "available": {
          "cached": true,
          "remote": true
        }
      }
    }
  ]
}
